Metadata-Version: 1.1
Name: collective.recipe.modwsgi
Version: 1.7
Summary: WSGI from buildout
Home-page: https://github.com/wichert/collective.recipe.modwsgi
Author: Wichert Akkerman
Author-email: wichert@wiggy.net
License: ZPL
Keywords: wsgi buildout
Platform: UNKNOWN
Classifier: Development Status :: 5 - Production/Stable
Classifier: Framework :: Buildout :: Recipe
Classifier: Intended Audience :: Developers
Classifier: Intended Audience :: System Administrators
Classifier: License :: OSI Approved :: Zope Public License
Classifier: Programming Language :: Python :: 2
Classifier: Programming Language :: Python :: 2.4
Classifier: Programming Language :: Python :: 2.5
Classifier: Programming Language :: Python :: 2.6
Classifier: Programming Language :: Python :: 2.7
